odoo9_addon_product_variant_standard_price_update-9.0.1.0.0-py2.7-nspkg.pth
odoo9_addon_product_variant_standard_price_update-9.0.1.0.0.dist-info/DESCRIPTION.rst
odoo9_addon_product_variant_standard_price_update-9.0.1.0.0.dist-info/METADATA
odoo9_addon_product_variant_standard_price_update-9.0.1.0.0.dist-info/RECORD
odoo9_addon_product_variant_standard_price_update-9.0.1.0.0.dist-info/WHEEL
odoo9_addon_product_variant_standard_price_update-9.0.1.0.0.dist-info/metadata.json
odoo9_addon_product_variant_standard_price_update-9.0.1.0.0.dist-info/namespace_packages.txt
odoo9_addon_product_variant_standard_price_update-9.0.1.0.0.dist-info/top_level.txt
odoo_addons/product_variant_standard_price_update/README.rst
odoo_addons/product_variant_standard_price_update/__init__.py
odoo_addons/product_variant_standard_price_update/__openerp__.py
odoo_addons/product_variant_standard_price_update/i18n/es.po
odoo_addons/product_variant_standard_price_update/models/__init__.py
odoo_addons/product_variant_standard_price_update/models/product.py
odoo_addons/product_variant_standard_price_update/static/description/icon.png
odoo_addons/product_variant_standard_price_update/tests/__init__.py
odoo_addons/product_variant_standard_price_update/tests/test_product_variant_standard_price_update.py
odoo_addons/product_variant_standard_price_update/views/product_view.xml
